InvestmentToolkit/__init__.py
InvestmentToolkit/itk.py
InvestmentToolkit-0.0.4.dist-info/LICENSE
InvestmentToolkit-0.0.4.dist-info/METADATA
InvestmentToolkit-0.0.4.dist-info/WHEEL
InvestmentToolkit-0.0.4.dist-info/top_level.txt
InvestmentToolkit-0.0.4.dist-info/RECORD
